LICENSE.txt
MANIFEST.in
README.md
setup.py
prefpy/__init__.py
prefpy/aggregate.py
prefpy/distributions.py
prefpy/evbwie.py
prefpy/gmm_mixpl.py
prefpy/gmm_mixpl_moments.py
prefpy/gmm_mixpl_objectives.py
prefpy/gmmra.py
prefpy/mmgbtl.py
prefpy/plackettluce.py
prefpy/stats.py
prefpy/util.py
prefpy.egg-info/PKG-INFO
prefpy.egg-info/SOURCES.txt
prefpy.egg-info/dependency_links.txt
prefpy.egg-info/not-zip-safe
prefpy.egg-info/top_level.txt