Metadata-Version: 1.1
Name: prefpy
Version: 0.8.1
Summary: Rank aggregation algorithms
Home-page: https://github.com/xialirong/prefpy
Author: Peter Piech
Author-email: UNKNOWN
License: GPL-3
Download-URL: https://github.com/xialirong/prefpy/archive/v0.8.1.tar.gz
Platform: UNKNOWN
Classifier: Development Status :: 3 - Alpha
Classifier: License :: OSI Approved :: GNU General Public License v3 (GPLv3)
Classifier: Programming Language :: Python :: 3.4
Classifier: Programming Language :: Python :: 3.5
Classifier: Intended Audience :: Science/Research
Classifier: Topic :: Scientific/Engineering
